gnarly/__init__.py
gnarly/constants.py
gnarly/errors.py
gnarly/types.py
gnarly/utils/__init__.py
gnarly/utils/io.py
gnarly/utils/code/__init__.py
gnarly/utils/code/projects.py
gnarly/utils/llm/__init__.py
gnarly/utils/llm/chatgpt.py
gnarly/utils/llm/claude.py
gnarly/utils/llm/interfaces.py
gnarly/utils/llm/models.py
gnarly-0.0.0.dev13.dist-info/METADATA
gnarly-0.0.0.dev13.dist-info/WHEEL
gnarly-0.0.0.dev13.dist-info/entry_points.txt
gnarly-0.0.0.dev13.dist-info/RECORD
