Metadata-Version: 2.4
Name: gnarly
Version: 0.0.0.dev13
Summary: A sophisticated, general-use abstraction layer for the lazy.
Author-email: "K. LeBryce" <k.lebryce@pm.me>
Requires-Python: >=3.10
Requires-Dist: python-dotenv>=1.1.0
Requires-Dist: starch
